databricksPackageVTn/__init__.py
databricksPackageVTn/module1.py
databricksPackageVTn/module2.py
databricksPackageVTF-0.9.dist-info/METADATA
databricksPackageVTF-0.9.dist-info/WHEEL
databricksPackageVTF-0.9.dist-info/top_level.txt
databricksPackageVTF-0.9.dist-info/RECORD
